LICENSE
README.md
setup.cfg
setup.py
Topsis_Pranjal_102003623/Topsis_Pranjal_102003623.py
Topsis_Pranjal_102003623.egg-info/PKG-INFO
Topsis_Pranjal_102003623.egg-info/SOURCES.txt
Topsis_Pranjal_102003623.egg-info/dependency_links.txt
Topsis_Pranjal_102003623.egg-info/entry_points.txt
Topsis_Pranjal_102003623.egg-info/requires.txt
Topsis_Pranjal_102003623.egg-info/top_level.txt