Metadata-Version: 2.1
Name: Topsis-Pranjal-102003623
Version: 1.0.1
Summary: This is a Python library for handling problems related to Multiple Criteria Decision Making(MCDM)
Home-page: https://github.com/Pranjal283/Topsis_Pranjal_102003623
Author: Pranjal Sharma
Author-email: pranjal28sharma@gmail.com
License: MIT
Classifier: License :: OSI Approved :: MIT License
Classifier: Programming Language :: Python :: 3.6
Classifier: Programming Language :: Python :: 3.7
Classifier: Programming Language :: Python :: 3.8
License-File: LICENSE
